pypapers/VERSION.py
pypapers/__init__.py
pypapers/cli.py
pypapers/helpers.py
pypapers/search.py
pypapers/tests/__init__.py
pypapers/tests/quicktest.py
pypapers/tests/test_one.py
pypapers-0.2.dist-info/METADATA
pypapers-0.2.dist-info/WHEEL
pypapers-0.2.dist-info/entry_points.txt
pypapers-0.2.dist-info/top_level.txt
pypapers-0.2.dist-info/RECORD
