Metadata-Version: 2.1
Name: pypapers
Version: 0.2
Summary: Python helper for working with a documents folder on OSx.
Home-page: https://github.com/lambdamusic/pypapers
License: UNKNOWN
Platform: UNKNOWN
Requires-Dist: Click
Requires-Dist: mdfind
Requires-Dist: psutil
Requires-Dist: public
Requires-Dist: runcmd
Requires-Dist: values
